LICENSE
transparentemail/__init__.py
transparentemail/services/Emails/__init__.py
transparentemail/services/Emails/editableEmail.py
transparentemail/services/Emails/email.py
transparentemail/services/Emails/emailException.py
transparentemail/services/__init__.py
transparentemail/services/gmailCom.py
transparentemail/services/outlookCom.py
transparentemail/services/serviceEmail.py
transparentemail/services/www33MailCom.py
transparentemail/services/yahooCom.py
transparentemail/src.py
transparentemail-0.1.2.dist-info/LICENSE
transparentemail-0.1.2.dist-info/WHEEL
transparentemail-0.1.2.dist-info/METADATA
transparentemail-0.1.2.dist-info/RECORD
