Metadata-Version: 2.1
Name: transparentemail
Version: 0.1.2
Summary: Transparent Email clears aliases from email address
Home-page: https://github.com/akash-codes93/TransparentEmail
License: MIT
Keywords: transparentemail,email alias,email
Author: Akash Gupta
Requires-Python: >=3.6.2,<4.0.0
Classifier: License :: OSI Approved :: MIT License
Classifier: Programming Language :: Python :: 3
Classifier: Programming Language :: Python :: 3.7
Classifier: Programming Language :: Python :: 3.8
Classifier: Programming Language :: Python :: 3.9
Project-URL: Repository, https://github.com/akash-codes93/TransparentEmail
